{
  "5": {
    "FF": {
      "1007": 0.3333333333333333,
      "4": 0.6666666666666666
    },
    "PF": {
      "1007": {
        "((0, (0,)), (2, (0,)), (6, (-71, -68, -67)))": 1.0,
        "RANDOM": 0,
        "MAX": [
          3,
          6,
          -71,
          0
        ]
      },
      "4": {
        "(0, 4, 11, 13, 15)": 1.0,
        "RANDOM": 0,
        "MAX": 15
      }
    }
  },
  "6": {
    "FF": {
      "4": 0.2,
      "1007": 0.8
    },
    "PF": {
      "4": {
        "(0, 1, 7, 10, 13, 15)": 1.0,
        "RANDOM": 0,
        "MAX": 15
      },
      "1007": {
        "((0, (0,)), (1, (0,)), (2, (-1, 0)), (3, (-1,)), (6, (1,)))": 1.0,
        "RANDOM": 0,
        "MAX": [
          5,
          6,
          -1,
          1
        ]
      }
    }
  },
  "7": {
    "FF": {
      "1007": 0.5,
      "1001": 0.5
    },
    "PF": {
      "1007": {
        "((0, (0,)), (1, (-1,)), (6, (0,)), (7, (-1,)), (13, (0,)), (15, (-1, 0)))": 1.0,
        "RANDOM": 0,
        "MAX": [
          6,
          15,
          -1,
          0
        ]
      },
      "1001": {
        "((0, (36,)), (1, (36,)), (2, (36,)), (3, (36,)), (4, (36,)), (5, (0, 2)))": 1.0,
        "RANDOM": 0,
        "MAX": [
          5,
          36
        ]
      }
    }
  },
  "8": {
    "FF": {
      "1007": 0.6666666666666666,
      "4": 0.3333333333333333
    },
    "PF": {
      "1007": {
        "((0, (0,)), (2, (1,)), (3, (0,)), (5, (0, 1)), (6, (0,)), (11, (0,)), (13, (1,)))": 0.5,
        "((0, (-1, 0)), (1, (-1,)), (4, (0,)), (7, (0,)), (12, (-1, 0)), (14, (0,)))": 0.5,
        "RANDOM": 0,
        "MAX": [
          7,
          14,
          -1,
          1
        ]
      },
      "4": {
        "(0, 1, 2, 3, 6, 8, 10, 11)": 1.0,
        "RANDOM": 0,
        "MAX": 11
      }
    }
  },
  "9": {
    "FF": {
      "1007": 1.0
    },
    "PF": {
      "1007": {
        "((0, (3, 0, 2)), (1, (0,)), (2, (0,)), (3, (0, 1)), (5, (3, -1)))": 0.5,
        "((0, (0,)), (2, (0,)), (3, (0,)), (7, (-1, 0)), (8, (0,)), (10, (0,)), (11, (-1,)), (12, (0,)))": 0.25,
        "((0, (0,)), (2, (0,)), (3, (0,)), (6, (-1,)), (7, (0,)), (8, (0,)), (10, (-1,)), (11, (-1, 0)))": 0.25,
        "RANDOM": 0,
        "MAX": [
          8,
          12,
          -1,
          3
        ]
      }
    }
  },
  "10": {
    "FF": {
      "1007": 1.0
    },
    "PF": {
      "1007": {
        "((0, (0, 2)), (1, (1,)), (2, (0,)), (3, (1,)), (4, (0, 1)), (5, (0, 2, 3)))": 0.14285714285714285,
        "((0, (0,)), (2, (0,)), (3, (0,)), (6, (-1, 0)), (8, (0,)), (10, (0,)), (12, (0,)), (13, (-1,)), (15, (0,)))": 0.14285714285714285,
        "((0, (2,)), (2, (0, 1, 3)), (3, (2,)), (4, (0, 3)), (5, (0, 1)), (6, (3,)))": 0.09523809523809523,
        "((0, (0,)), (1, (0,)), (3, (0,)), (4, (1,)), (5, (0,)), (7, (1,)), (11, (1,)), (13, (0,)), (14, (1,)), (15, (1,)))": 0.09523809523809523,
        "RANDOM": 0.5238095238095237,
        "MAX": [
          10,
          15,
          -3,
          4
        ]
      }
    }
  },
  "11": {
    "FF": {
      "1007": 1.0
    },
    "PF": {
      "1007": {
        "((0, (0,)), (1, (-1,)), (2, (-2, 1)), (3, (-3, -2, 0)), (5, (1,)), (6, (-3, -1, 0)))": 0.08823529411764706,
        "((0, (-2, -1, 0, 1)), (2, (-3, 1)), (3, (-1, 1)), (4, (-3, 0)), (5, (0,)))": 0.08823529411764706,
        "((0, (0,)), (1, (-1,)), (3, (0,)), (4, (-1,)), (5, (-1,)), (6, (0,)), (9, (0,)), (11, (-1, 0)), (13, (-1,)), (14, (0,)))": 0.058823529411764705,
        "((0, (-1, 0)), (1, (0,)), (2, (-1, 0)), (3, (0,)), (5, (0,)), (6, (0,)), (9, (-1,)), (11, (0,)), (14, (0,)))": 0.058823529411764705,
        "((0, (0,)), (2, (-1, 0)), (3, (0, 1, 3)), (4, (2, 3)), (5, (3,)), (6, (-1, 2)))": 0.058823529411764705,
        "((0, (-1, 0, 1, 2, 3)), (1, (-1,)), (2, (0,)), (3, (0,)), (4, (0,)), (5, (-2,)), (6, (-2,)))": 0.058823529411764705,
        "((0, (-2, 0)), (1, (-2, 1)), (2, (0,)), (3, (-1, 0)), (4, (-1, 0, 1)), (6, (-2,)))": 0.058823529411764705,
        "((0, (1, 2)), (1, (0,)), (2, (0,)), (3, (-2, 0, 1)), (4, (-2, 0)), (5, (-2, 2)))": 0.058823529411764705,
        "RANDOM": 0.4705882352941177,
        "MAX": [
          11,
          15,
          -4,
          4
        ]
      }
    }
  },
  "12": {
    "FF": {
      "1007": 1.0
    },
    "PF": {
      "1007": {
        "((0, (0, 1)), (2, (1,)), (3, (0,)), (5, (0,)), (6, (1,)), (7, (1,)), (8, (0,)), (9, (0, 1)), (10, (0,)), (11, (0,)))": 0.06666666666666667,
        "((0, (1,)), (1, (1,)), (3, (1,)), (4, (0,)), (5, (0,)), (6, (0,)), (7, (0, 1)), (9, (0,)), (11, (0,)), (13, (0,)), (14, (0,)))": 0.06666666666666667,
        "RANDOM": 0.8666666666666668,
        "MAX": [
          11,
          15,
          -4,
          4
        ]
      }
    }
  },
  "13": {
    "FF": {
      "1007": 0.9904761904761905,
      "1006": 0.009523809523809525
    },
    "PF": {
      "1007": {
        "((0, (0, 2)), (1, (-1, 0, 1)), (2, (-1,)), (3, (-1, 2)), (4, (-1, 0, 1)), (6, (-2, 0)))": 0.057692307692307696,
        "((0, (-2, -1, 0)), (1, (-3, -2, 0)), (2, (-3, -1)), (3, (-2,)), (4, (0,)), (5, (0,)), (6, (-3, -1)))": 0.057692307692307696,
        "RANDOM": 0.8846153846153848,
        "MAX": [
          13,
          15,
          -4,
          4
        ]
      },
      "1006": {
        "((0, (0,)), (1, (-1, 0)), (2, (-1, 0)), (3, (0,)), (4, (0, 1)), (5, (0, 1)))": 1.0,
        "RANDOM": 0,
        "MAX": [
          6,
          5,
          -2,
          1
        ]
      }
    }
  },
  "14": {
    "FF": {
      "1007": 0.9558823529411765,
      "1006": 0.04411764705882353
    },
    "PF": {
      "1007": {
        "((0, (0, 1, 3)), (1, (2, 3)), (2, (-1, 1, 2)), (3, (-1, 0)), (4, (-1, 0, 2)), (5, (0,)))": 0.05384615384615385,
        "RANDOM": 0.9461538461538456,
        "MAX": [
          13,
          15,
          -4,
          4
        ]
      },
      "1006": {
        "((0, (0,)), (1, (1, -1, 0)), (3, (1, -1, 0)), (4, (-1, 0)), (5, (1, -2, 0)), (6, (-1, 0)))": 0.6666666666666666,
        "((0, (0,)), (1, (0,)), (3, (-1, 0)), (4, (-1, 0)), (7, (-1, 0)), (9, (0,)), (10, (0,)), (11, (0,)), (12, (0,)), (14, (-1, 0)))": 0.16666666666666666,
        "((0, (0,)), (1, (0,)), (2, (0, 1)), (4, (0, 1)), (8, (0, 1)), (9, (0,)), (10, (0,)), (12, (0,)), (13, (0,)), (15, (0,)))": 0.16666666666666666,
        "RANDOM": 0,
        "MAX": [
          10,
          15,
          -2,
          1
        ]
      }
    }
  },
  "15": {
    "FF": {
      "1007": 0.9873417721518988,
      "1006": 0.012658227848101266
    },
    "PF": {
      "1007": {
        "RANDOM": 0.9999999999999989,
        "MAX": [
          14,
          15,
          -4,
          4
        ]
      },
      "1006": {
        "((0, (0,)), (2, (0, 2, 3)), (3, (0, 1, 2, 4)), (4, (0, 3)), (6, (0, 2, 3)))": 0.5,
        "((0, (0,)), (1, (1, -1, 0)), (2, (0,)), (3, (1, -1, 0)), (4, (-1, 0)), (5, (1, -2, 0)), (6, (-1, 0)))": 0.5,
        "RANDOM": 0,
        "MAX": [
          7,
          6,
          -2,
          4
        ]
      }
    }
  },
  "16": {
    "FF": {
      "1007": 0.9440559440559441,
      "1006": 0.04895104895104895,
      "4": 0.006993006993006993
    },
    "PF": {
      "1007": {
        "RANDOM": 1.000000000000001,
        "MAX": [
          15,
          15,
          -2884,
          4
        ]
      },
      "1006": {
        "((0, (0,)), (1, (-1, 0, 1)), (2, (0, -3, -2)), (4, (0, -3, -2)), (5, (0, -4)), (6, (0,)))": 0.5714285714285714,
        "((0, (0,)), (2, (0,)), (3, (0,)), (4, (0,)), (6, (0,)), (7, (0, 1)), (8, (0, 1)), (9, (0, 1)), (10, (0, 1)), (11, (0,)), (13, (0, 1)))": 0.2857142857142857,
        "((0, (0,)), (1, (0, 1)), (2, (0,)), (3, (3, 0, 2)), (4, (-1, 0, 2)), (5, (-1, 0, 1)), (6, (0, 1)))": 0.14285714285714285,
        "RANDOM": 0,
        "MAX": [
          11,
          13,
          -4,
          3
        ]
      },
      "4": {
        "(0, 1, 2, 3, 4, 5, 6, 7, 8, 9, 10, 11, 12, 13, 14, 15)": 1.0,
        "RANDOM": 0,
        "MAX": 15
      }
    }
  },
  "17": {
    "FF": {
      "1007": 0.958041958041958,
      "1006": 0.04195804195804196
    },
    "PF": {
      "1007": {
        "RANDOM": 0.999999999999999,
        "MAX": [
          15,
          15,
          -4,
          3
        ]
      },
      "1006": {
        "((0, (0,)), (1, (0, -3, -2)), (3, (0, -3)), (4, (0, -3)), (5, (0, -4, -2)), (6, (0, -4)))": 0.5,
        "((0, (0,)), (1, (0,)), (2, (0,)), (3, (-1, 0)), (5, (0,)), (6, (-1, 0)), (8, (0,)), (9, (-1, 0)), (12, (0,)), (13, (-1, 0)), (15, (-1, 0)))": 0.16666666666666666,
        "((0, (0,)), (1, (0, -2)), (2, (0,)), (3, (-1, 0)), (4, (0, -3)), (5, (0, -3, -2)), (6, (0, -4, -3)))": 0.16666666666666666,
        "((0, (0,)), (2, (0,)), (4, (-1, 0)), (5, (0,)), (6, (-1, 0)), (7, (-1, 0)), (8, (0,)), (9, (-1, 0)), (10, (-1, 0)), (11, (0,)), (12, (0,)))": 0.16666666666666666,
        "RANDOM": 0,
        "MAX": [
          11,
          15,
          -4,
          1
        ]
      }
    }
  },
  "18": {
    "FF": {
      "1007": 0.9844961240310077,
      "1006": 0.015503875968992248
    },
    "PF": {
      "1007": {
        "((0, (2, 3, -1)), (1, (2, -1, 0)), (2, (1, 2, 0)), (3, (1,)), (4, (1, 0)), (5, (1, -1, 0)), (6, (-2, -1, 0)))": 0.05511811023622047,
        "RANDOM": 0.9448818897637787,
        "MAX": [
          15,
          15,
          -4,
          2488
        ]
      },
      "1006": {
        "((0, (0,)), (1, (0, 1)), (2, (-3, -2, 0, 1)), (3, (0, 1)), (4, (-3, -2, 0, 1)), (5, (-3, -2, 0)), (6, (-1, 0)))": 0.5,
        "((0, (0,)), (1, (0, 1)), (2, (0, 1)), (3, (0,)), (5, (0,)), (6, (0,)), (7, (0, 1)), (8, (0,)), (9, (0, 1)), (10, (0,)), (11, (0,)), (12, (0,)), (14, (0,)))": 0.5,
        "RANDOM": 0,
        "MAX": [
          13,
          14,
          -3,
          1
        ]
      }
    }
  },
  "19": {
    "FF": {
      "1007": 0.9272727272727272,
      "1006": 0.07272727272727272
    },
    "PF": {
      "1007": {
        "((0, (0,)), (1, (0,)), (2, (0,)), (3, (-1,)), (4, (-1,)), (5, (-1, 0)), (7, (-1, 0)), (8, (-1,)), (10, (-1, 0)), (11, (-1, 0)), (12, (0,)), (13, (-1, 0)), (15, (-1, 0)))": 0.0784313725490196,
        "((0, (0, 1, 2, 3, 4)), (1, (0, 2)), (2, (0, 2, 3, 4)), (3, (0, 3)), (4, (0, 1, 3)), (5, (3,)), (6, (0, 3)))": 0.0784313725490196,
        "((0, (0,)), (1, (0,)), (2, (-1, 0)), (3, (-1,)), (4, (-1, 0)), (5, (0,)), (6, (-1,)), (7, (-1, 0)), (9, (0,)), (10, (0,)), (11, (0,)), (12, (-1, 0)), (13, (0,)), (14, (0,)), (15, (0,)))": 0.058823529411764705,
        "RANDOM": 0.7843137254901958,
        "MAX": [
          15,
          15,
          -4,
          4
        ]
      },
      "1006": {
        "((0, (0,)), (1, (-1, 0)), (2, (-2, 0)), (3, (0, 1)), (4, (-1, 0, 1)), (5, (-3, -2, 0)), (6, (-2, -1, 0, 1)))": 0.5,
        "((0, (0,)), (1, (0, 1, -2, -1)), (2, (0, -1)), (3, (0, -1)), (4, (0, 1, -2)), (5, (0, -2, -1)), (6, (0, -2)))": 0.25,
        "((0, (0,)), (1, (0,)), (2, (-1, 0)), (3, (0,)), (5, (-1, 0)), (7, (0,)), (8, (-1, 0)), (9, (0,)), (10, (-1, 0)), (11, (-1, 0)), (12, (0,)), (13, (0,)), (14, (-1, 0)))": 0.125,
        "((0, (0,)), (1, (-3, -2, 0, 1)), (2, (-3, 0, 1)), (3, (-1, 0, 1)), (4, (-3, -2, 0, 1)), (5, (-1, 0)), (6, (0,)))": 0.125,
        "RANDOM": 0,
        "MAX": [
          13,
          14,
          -3,
          1
        ]
      }
    }
  },
  "20": {
    "FF": {
      "1007": 0.9782608695652174,
      "1006": 0.021739130434782608
    },
    "PF": {
      "1007": {
        "((0, (0, 1, 2)), (1, (0, 1, 3)), (2, (3,)), (3, (0, 1, 2, -1)), (4, (1, -1)), (5, (0, 1, -1)), (6, (0, 2, -2, -1)))": 0.13333333333333333,
        "((0, (0, 1, 2)), (1, (0, 2)), (2, (0, 2, 3)), (3, (-1, 1, 3)), (4, (0, 1, 2)), (5, (-1, 0, 1, 2)), (6, (0, 2)))": 0.06666666666666667,
        "RANDOM": 0.7999999999999998,
        "MAX": [
          16,
          15,
          -4,
          4
        ]
      },
      "1006": {
        "((0, (0,)), (2, (-1, 0)), (3, (0,)), (4, (-1, 0)), (5, (0,)), (6, (0,)), (7, (-1, 0)), (8, (-1, 0)), (9, (0,)), (11, (-1, 0)), (12, (-1, 0)), (13, (0,)), (14, (-1, 0)))": 0.5,
        "((0, (0,)), (1, (1, 0)), (2, (1, -2, 0)), (3, (1, -1, 0)), (4, (1, -2, 0)), (5, (1, -3, 0)), (6, (-3, 0)))": 0.5,
        "RANDOM": 0,
        "MAX": [
          13,
          14,
          -3,
          2
        ]
      }
    }
  },
  "21": {
    "FF": {
      "1007": 0.813953488372093,
      "1006": 0.18604651162790697
    },
    "PF": {
      "1007": {
        "((0, (-2, -1, 0)), (1, (-2, -1, 1, -3)), (2, (-2, -1, 0, -3)), (3, (0, -3)), (4, (0, -3)), (5, (-2, 0, -3)), (6, (-2, 0, -3)))": 0.17142857142857143,
        "((0, (1, 2)), (1, (0,)), (2, (0, -2, -1)), (3, (0, 1, -2, -1)), (4, (0, 1, -2)), (5, (-3, -2, -1, 0, 1)), (6, (-3, -2, -1)))": 0.08571428571428572,
        "((0, (-1, 0)), (1, (-1, 0)), (2, (-1, 0)), (3, (-1, 0)), (4, (0,)), (6, (0,)), (7, (-1, 0)), (9, (-1, 0)), (10, (0,)), (11, (-1,)), (12, (0,)), (13, (0,)), (14, (-1, 0)), (15, (-1,)))": 0.08571428571428572,
        "((0, (-1, 0)), (1, (-1,)), (2, (-1, 0)), (3, (0,)), (4, (-1,)), (5, (0,)), (6, (-1, 0)), (7, (-1, 0)), (8, (-1, 0)), (9, (0,)), (12, (-1, 0)), (13, (-1, 0)), (14, (-1,)), (15, (0,)))": 0.05714285714285714,
        "((0, (-2, 0, 2)), (1, (0, 1, 2)), (2, (-1, 0, 1)), (3, (-2, -1, 1, 2)), (4, (-2, -1, 0, 1)), (5, (-2, -1, 0)), (6, (0,)))": 0.05714285714285714,
        "((0, (-1, 0)), (1, (0,)), (2, (-1, 0)), (3, (0,)), (5, (-1, 0)), (6, (-1, 0)), (7, (-1, 0)), (8, (-1,)), (9, (-1, 0)), (11, (-1, 0)), (12, (0,)), (13, (0,)), (15, (-1, 0)))": 0.05714285714285714,
        "((0, (-1, 0, 1, -3)), (1, (-2, -1, 0, 1)), (2, (-1, 0, 1, -3)), (3, (-2, -1, 0, -3)), (4, (0, -3)), (5, (0,)), (6, (-2, -4)))": 0.05714285714285714,
        "RANDOM": 0.42857142857142866,
        "MAX": [
          15,
          15,
          -4,
          4
        ]
      },
      "1006": {
        "((0, (0,)), (1, (-1, 0, 1, -3)), (2, (-1, 0, 1)), (3, (-2, -1, 0, -3)), (4, (-2, 0, -3)), (5, (-2, 0, -3)))": 0.375,
        "((0, (0,)), (1, (1, 0)), (2, (1, -2, 0)), (3, (1, -1, 0)), (4, (1, -2, 0)), (5, (1, -3, 0)), (6, (-3, -2, 0)))": 0.25,
        "((0, (0,)), (1, (-1, 0, 2)), (2, (-1, 0, 1, 2)), (3, (0, 2)), (4, (-2, -1, 0)), (5, (0, 2)), (6, (-2, 0, 1, 2)))": 0.125,
        "((0, (0,)), (1, (-2, 0, 2)), (2, (0, 2)), (3, (0, 1, 2)), (4, (-2, -1, 0, 1, 2)), (5, (-2, 0, 1)), (6, (-2, 0, 1)))": 0.125,
        "((0, (0,)), (1, (2, -1, 0)), (2, (2, 0, 1)), (3, (2, -1, 0)), (4, (2, 0, 1)), (5, (2, 0, 1)), (6, (0, 1)))": 0.125,
        "RANDOM": 0,
        "MAX": [
          7,
          6,
          -3,
          3
        ]
      }
    }
  },
  "22": {
    "FF": {
      "1007": 0.75,
      "1006": 0.25
    },
    "PF": {
      "1007": {
        "((0, (0, 1, 2)), (1, (-1, 0)), (2, (-1, 2, 3)), (3, (1, 2, 3)), (4, (-1, 0, 1, 2)), (5, (-1, 0, 1)), (6, (-1, 0, 1, 2)))": 0.4666666666666667,
        "((0, (0, 1)), (1, (0,)), (2, (0, 1)), (3, (0, 1)), (4, (0,)), (5, (1,)), (6, (0, 1)), (7, (0, 1)), (8, (0, 1)), (9, (0,)), (10, (1,)), (12, (0,)), (14, (0, 1)), (15, (0, 1)))": 0.06666666666666667,
        "((0, (0, 1)), (1, (0, 1)), (2, (0, 1)), (3, (0,)), (5, (0, 1)), (6, (0,)), (7, (0, 1)), (8, (0, 1)), (9, (1,)), (10, (0, 1)), (11, (1,)), (12, (0, 1)), (14, (0, 1)))": 0.06666666666666667,
        "((0, (-1,)), (1, (-1, 0)), (2, (0,)), (3, (-1, 0)), (4, (-1, 0)), (5, (-1, 0)), (6, (-1,)), (7, (0,)), (8, (0,)), (9, (-1, 0)), (10, (0,)), (11, (-1,)), (12, (-1, 0)), (13, (-1, 0)), (14, (0,)))": 0.06666666666666667,
        "((0, (0, 1, 2, 3)), (1, (-1, 0, 2, 3)), (2, (-1, 1, 3)), (3, (-1, 0, 1, 3)), (4, (0, 1, 2, 3)), (5, (0, 1, 2)))": 0.06666666666666667,
        "((0, (0, 1)), (1, (3,)), (2, (-1, 0, 2)), (3, (-1, 0, 1, 2, 3)), (4, (-1, 0, 1, 2, 3)), (5, (2, 3)), (6, (-1, 0, 1, 2)))": 0.06666666666666667,
        "((0, (-1, 0)), (1, (-1, 0)), (2, (-1, 0)), (3, (-1, 0)), (4, (0,)), (6, (-1, 0)), (7, (-1, 0)), (9, (-1, 0)), (10, (0,)), (11, (-1,)), (12, (0,)), (13, (0,)), (14, (-1, 0)), (15, (-1,)))": 0.06666666666666667,
        "((0, (0, 1, 2, 3, 4)), (1, (2,)), (2, (0, 1)), (3, (2, 3, 0, 1)), (4, (2, 3, 0, 1)), (5, (2, 0)), (6, (2, 3, 0, 1)))": 0.06666666666666667,
        "((0, (0, 1, 2)), (1, (-1, 0, 1, 2)), (2, (-2, -1, 0, 1, 2)), (3, (-2, -1, 0, 1, 2)), (4, (0, 1)), (5, (-1,)), (6, (-2, 0)))": 0.06666666666666667,
        "RANDOM": 0,
        "MAX": [
          15,
          15,
          -2,
          4
        ]
      },
      "1006": {
        "((0, (0, -2)), (1, (0, -2, -1)), (2, (0, -2)), (3, (0, -2, -1)), (4, (0, -2, -1)), (5, (0, -3, -2, -1)), (6, (0, -3, -2, -1)))": 0.4,
        "((0, (0,)), (1, (0, 1)), (2, (0,)), (3, (0, 1)), (5, (0,)), (6, (0,)), (7, (0,)), (8, (0, 1)), (9, (0,)), (10, (0, 1)), (11, (0, 1)), (12, (0, 1)), (13, (0, 1)), (15, (0, 1)))": 0.2,
        "((0, (0,)), (1, (0, 1)), (2, (0, 1, -2)), (3, (-1, 0, 1, -2)), (4, (0, 1, -2)), (5, (-1, 0, -2)), (6, (-1, 0, 1, -2)))": 0.2,
        "((0, (0,)), (1, (1, 2, 4, 0)), (2, (1, 2, 3, 0)), (3, (3, 0)), (4, (3, 0)), (5, (1, 3, 0)), (6, (1, 3, 0)))": 0.2,
        "RANDOM": 0,
        "MAX": [
          14,
          15,
          -3,
          4
        ]
      }
    }
  },
  "23": {
    "FF": {
      "1007": 0.6923076923076923,
      "1006": 0.3076923076923077
    },
    "PF": {
      "1007": {
        "((0, (0,)), (1, (0, 1)), (2, (0, 1)), (3, (0,)), (4, (0, 1)), (6, (1,)), (7, (0, 1)), (8, (0, 1)), (9, (1,)), (10, (0, 1)), (11, (0, 1)), (12, (1,)), (13, (0,)), (14, (0,)), (15, (0, 1)))": 0.1111111111111111,
        "((0, (0, 1)), (1, (0,)), (2, (0,)), (3, (0, 1)), (4, (0,)), (6, (0, 1)), (7, (1,)), (8, (1,)), (9, (0,)), (10, (0, 1)), (11, (1,)), (12, (0, 1)), (13, (0, 1)), (14, (0, 1)), (15, (0, 1)))": 0.1111111111111111,
        "((0, (1, 2, 3, 0)), (1, (2, 4, 0)), (2, (0, 1, 2, 3, 4)), (3, (0,)), (4, (1, 3)), (5, (1, 2, 3, 0)), (6, (1, 2, 3, 0)))": 0.1111111111111111,
        "((0, (-1, 0)), (1, (-1, 0)), (2, (-1,)), (3, (-1, 0)), (4, (-1, 0)), (5, (-1,)), (6, (0,)), (7, (0,)), (8, (0,)), (9, (0,)), (10, (-1, 0)), (11, (-1, 0)), (12, (-1, 0)), (13, (0,)), (14, (0,)), (15, (-1,)))": 0.1111111111111111,
        "((0, (-1,)), (1, (-1, 0)), (2, (-1, 0)), (3, (0,)), (4, (-1, 0)), (5, (-1, 0)), (6, (-1,)), (7, (0,)), (8, (-1, 0)), (9, (0,)), (10, (-1, 0)), (11, (0,)), (12, (-1, 0)), (13, (0,)), (14, (-1,)), (15, (-1,)))": 0.1111111111111111,
        "((0, (-1, 0)), (1, (-1,)), (2, (-1, 0)), (3, (-1, 0)), (4, (0,)), (5, (-1, 0)), (6, (-1, 0)), (7, (0,)), (8, (-1, 0)), (9, (0,)), (11, (-1, 0)), (12, (-1, 0)), (13, (0,)), (14, (0,)), (15, (0,)))": 0.1111111111111111,
        "((0, (-1, 0)), (1, (-1,)), (2, (-1, 0)), (3, (0,)), (4, (-1, 0)), (5, (0,)), (6, (0,)), (7, (-1, 0)), (8, (-1, 0)), (9, (-1, 0)), (10, (0,)), (12, (-1, 0)), (14, (-1, 0)), (15, (-1, 0)))": 0.1111111111111111,
        "((0, (-1,)), (1, (0,)), (2, (-1, 0)), (3, (0,)), (4, (-1, 0)), (5, (-1, 0)), (6, (0,)), (7, (0,)), (8, (0,)), (9, (0,)), (11, (-1, 0)), (12, (-1, 0)), (13, (-1, 0)), (14, (-1, 0)), (15, (-1, 0)))": 0.1111111111111111,
        "((0, (-2, -1, 0)), (1, (-3, -2, -1, 1)), (2, (-3, -1, 0, 1)), (3, (-3, -2, -1, 0)), (4, (-3, 0)), (5, (-3, -2, 0)), (6, (-2, -1, 0)))": 0.1111111111111111,
        "RANDOM": 0,
        "MAX": [
          16,
          15,
          -3,
          4
        ]
      },
      "1006": {
        "((0, (0, -2, -1)), (1, (0, -2, -1)), (2, (0, -2, -1)), (3, (0, -2, -1)), (4, (0, -2, -1)), (5, (0, -3, -2, -1)), (6, (0, -3, -2, -1)))": 0.75,
        "((0, (0,)), (1, (2, -1, 0)), (2, (2, 0, 1)), (3, (2, -1, 0, 1)), (4, (2, 0, 1)), (5, (2, 0, 1)), (6, (-2, 0, 1)))": 0.25,
        "RANDOM": 0,
        "MAX": [
          7,
          6,
          -3,
          3
        ]
      }
    }
  },
  "24": {
    "FF": {
      "1007": 1.0
    },
    "PF": {
      "1007": {
        "((0, (1, 2, 3, 4)), (1, (0, 1)), (2, (0, 3, 4)), (3, (0, 2, 3, 4)), (4, (0, 1, 2, 3)), (5, (0, 1, 2)), (6, (0, 1, 2, 3)))": 0.5,
        "((0, (-1, 0)), (1, (-1, 0)), (2, (0,)), (3, (0,)), (4, (-1, 0)), (5, (-1, 0)), (6, (-1,)), (7, (-1, 0)), (8, (-1, 0)), (9, (0,)), (10, (-1, 0)), (11, (0,)), (12, (-1, 0)), (13, (0,)), (15, (-1, 0)))": 0.25,
        "((0, (0,)), (1, (1,)), (2, (0, 1)), (3, (0,)), (4, (0, 1)), (5, (0, 1)), (6, (0,)), (7, (1,)), (8, (0, 1)), (9, (0,)), (10, (0, 1)), (11, (0, 1)), (13, (0, 1)), (14, (0, 1)), (15, (0, 1)))": 0.25,
        "RANDOM": 0,
        "MAX": [
          15,
          15,
          -1,
          4
        ]
      }
    }
  },
  "25": {
    "FF": {
      "1007": 0.4,
      "1006": 0.6
    },
    "PF": {
      "1007": {
        "((0, (-1, 0)), (1, (-1, 0)), (2, (-1, 0)), (3, (-1, 0)), (4, (0,)), (5, (-1, 0)), (6, (-1,)), (7, (0,)), (8, (-1, 0)), (9, (-1, 0)), (10, (-1, 0)), (11, (-1, 0)), (12, (0,)), (13, (0,)), (15, (-1, 0)))": 0.5,
        "((0, (-2, -1, 0, 1, 2)), (1, (-2, -1, 0, 1, 2)), (2, (-1, 1, 2, -2)), (3, (-1, 0, 1)), (4, (0, 1, -2)), (5, (0, -2)), (6, (0, 1, -3)))": 0.5,
        "RANDOM": 0,
        "MAX": [
          15,
          15,
          -3,
          2
        ]
      },
      "1006": {
        "((0, (0,)), (1, (0, 1)), (2, (0, 1)), (3, (0, 1)), (4, (0, 1)), (5, (0, 1)), (6, (0, 1)), (7, (0, 1)), (8, (0,)), (9, (0,)), (11, (0, 1)), (12, (0, 1)), (13, (0, 1)), (15, (0, 1)))": 0.3333333333333333,
        "((0, (0,)), (1, (0, 2, 3, 4)), (2, (0, 1, 2, 3, 4)), (3, (0, 1, 2, 3, 4)), (4, (0, 1, 2, 3)), (5, (0, 2)), (6, (0,)))": 0.3333333333333333,
        "((0, (0,)), (1, (0, 1, 2, -1)), (2, (0, 1, -1)), (3, (0, 1, -2)), (4, (0, 1, -2, -1)), (5, (0, -2, -1)), (6, (0, 1, -3)))": 0.3333333333333333,
        "RANDOM": 0,
        "MAX": [
          14,
          15,
          -3,
          4
        ]
      }
    }
  },
  "26": {
    "FF": {
      "1006": 0.3333333333333333,
      "1007": 0.6666666666666666
    },
    "PF": {
      "1006": {
        "((0, (0,)), (1, (0, 1)), (2, (0, 1)), (3, (0, 1)), (4, (0, 1)), (5, (0, 1)), (6, (0, 1)), (7, (0, 1)), (8, (0, 1)), (9, (0,)), (10, (0, 1)), (11, (0, 1)), (13, (0, 1)), (14, (0,)))": 1.0,
        "RANDOM": 0,
        "MAX": [
          14,
          14,
          0,
          1
        ]
      },
      "1007": {
        "((0, (-1, 0)), (1, (-2, 0, 1)), (2, (-97, 2, -181)), (3, (-2, -97, -1, 1, 2)), (4, (-1, 0, 1, 2, -181)), (5, (-265, 0)), (6, (-265, -2, -1, 0, 1, -181)))": 0.5,
        "((0, (251, 84, 0)), (1, (-716, -715, 84, -712, 0, 167)), (2, (251, -715, -713, 0)), (3, (-716, 167, 0)), (4, (83, 167, -712)), (5, (83, -716, -713, 250, 167)), (6, (83, 250)))": 0.5,
        "RANDOM": 0,
        "MAX": [
          7,
          6,
          -716,
          251
        ]
      }
    }
  },
  "27": {
    "FF": {
      "1007": 1.0
    },
    "PF": {
      "1007": {
        "((0, (0, 1)), (1, (0, 1)), (2, (0, 1)), (3, (0,)), (4, (1,)), (5, (0, 1)), (6, (0, 1)), (7, (0, 1)), (8, (0,)), (9, (0, 1)), (10, (1,)), (11, (0, 1)), (12, (0,)), (13, (0, 1)), (14, (0, 1)), (15, (0, 1)))": 0.3333333333333333,
        "((0, (0, 1, 2, 3, 4)), (1, (3, 0, 1, 2)), (2, (3, 1, 2)), (3, (3, 0, 1)), (4, (-1, 0, 2)), (5, (3, -1, 0, 2)), (6, (-1, 0, 1, 2, 3)))": 0.3333333333333333,
        "((0, (0, 3729, 3562)), (1, (3478, -1, 1, 3562)), (2, (-3, 3478, 0)), (3, (3729, 3478, -3, -2, -1, 3645)), (4, (3645, -2, 0, 1)), (5, (3478, 3645, -2, 1)), (6, (3645, 0, 3561)))": 0.3333333333333333,
        "RANDOM": 0,
        "MAX": [
          16,
          15,
          -3,
          3729
        ]
      }
    }
  },
  "28": {
    "FF": {
      "1007": 1.0
    },
    "PF": {
      "1007": {
        "((0, (-1, 0)), (1, (0,)), (2, (-1, 0)), (3, (-1, 0)), (4, (-1, 0)), (5, (-1, 0)), (6, (-1, 0)), (7, (0,)), (8, (-1, 0)), (9, (-1,)), (10, (-1, 0)), (11, (0,)), (12, (-1, 0)), (13, (-1, 0)), (14, (-1, 0)), (15, (-1, 0)))": 0.2,
        "((0, (0, 1)), (1, (0, 1)), (2, (0, 1)), (3, (0, 1)), (4, (0,)), (5, (0, 1)), (6, (0, 1)), (7, (1,)), (8, (0,)), (9, (0, 1)), (10, (0, 1)), (11, (0, 1)), (12, (0, 1)), (13, (0, 1)), (14, (0, 1)), (15, (1,)))": 0.2,
        "((0, (-1, 0)), (1, (0,)), (2, (-1, 0)), (3, (-1, 0)), (4, (-1, 0)), (5, (-1, 0)), (6, (-1, 0)), (7, (0,)), (8, (-1, 0)), (9, (-1, 0)), (10, (0,)), (11, (-1, 0)), (12, (-1, 0)), (13, (-1, 0)), (14, (-1, 0)), (15, (-1,)))": 0.2,
        "((0, (0, 1)), (1, (1,)), (2, (0, 1)), (3, (1,)), (4, (0,)), (5, (0, 1)), (6, (0, 1)), (7, (0, 1)), (8, (0, 1)), (9, (0, 1)), (10, (0, 1)), (11, (0,)), (12, (0, 1)), (13, (0, 1)), (14, (0, 1)), (15, (0, 1)))": 0.2,
        "((0, (0, 1, 2, 3, 4)), (1, (3, 1, 2)), (2, (3, 0, 1, 2)), (3, (0, 1, 2)), (4, (-1, 0, 1, 2, 3)), (5, (3, -1, 0, 2)), (6, (3, -1, 0, 1)))": 0.2,
        "RANDOM": 0,
        "MAX": [
          16,
          15,
          -1,
          4
        ]
      }
    }
  },
  "29": {
    "FF": {
      "1007": 0.25,
      "1006": 0.75
    },
    "PF": {
      "1007": {
        "((0, (0, 1)), (1, (0,)), (2, (0, 1)), (3, (0, 1)), (4, (0, 1)), (5, (0, 1)), (6, (0, 1)), (7, (1,)), (8, (0, 1)), (9, (0, 1)), (10, (0, 1)), (11, (0, 1)), (12, (0,)), (13, (0, 1)), (14, (0, 1)), (15, (0, 1)))": 0.5,
        "((0, (0, 1)), (1, (0, 1)), (2, (1,)), (3, (0, 1)), (4, (0,)), (5, (0, 1)), (6, (0, 1)), (7, (0,)), (8, (0, 1)), (9, (0, 1)), (10, (0, 1)), (11, (0, 1)), (12, (0, 1)), (13, (0, 1)), (14, (0, 1)), (15, (0, 1)))": 0.5,
        "RANDOM": 0,
        "MAX": [
          16,
          15,
          0,
          1
        ]
      },
      "1006": {
        "((0, (0,)), (1, (-2, -1, 0, 1, 2)), (2, (-2, -1, 0, 1, 2)), (3, (-2, -1, 0, 1, 2)), (4, (-2, -1, 0)), (5, (-1, 0, 1)), (6, (-2, -1, 0, 1)))": 0.3333333333333333,
        "((0, (0,)), (1, (-1, 0, 1, 2, 3)), (2, (-1, 0, 1, 3)), (3, (-1, 0, 2, 3)), (4, (-1, 0, 1, 2)), (5, (0, 1, 2)), (6, (-1, 0, 1, 2)))": 0.3333333333333333,
        "((0, (0,)), (1, (0, 1)), (2, (0, 1)), (3, (0, 1)), (4, (0, 1)), (5, (0,)), (6, (0,)), (7, (0,)), (8, (0, 1)), (9, (0, 1)), (10, (0, 1)), (11, (0, 1)), (12, (0, 1)), (13, (0, 1)), (14, (0, 1)), (15, (0, 1)))": 0.16666666666666666,
        "((0, (0,)), (1, (1, 2, 3, 0)), (2, (1, 2, -1, 0)), (3, (1, -1, 0)), (4, (1, 2, -1, 0)), (5, (2, -2, -1, 0)), (6, (-2, -1, 0, 1, 2)))": 0.16666666666666666,
        "RANDOM": 0,
        "MAX": [
          16,
          15,
          -2,
          3
        ]
      }
    }
  },
  "30": {
    "FF": {
      "1007": 0.3333333333333333,
      "1006": 0.6666666666666666
    },
    "PF": {
      "1007": {
        "((0, (0,)), (1, (0, 1)), (2, (0, 1)), (3, (0, 1)), (4, (1,)), (5, (0, 1)), (6, (0, 1)), (7, (0, 1)), (8, (0, 1)), (9, (0, 1)), (10, (0, 1)), (11, (0, 1)), (12, (0, 1)), (13, (0, 1)), (14, (0, 1)), (15, (0, 1)))": 0.21739130434782608,
        "((0, (0, 1)), (1, (0, 1)), (2, (1,)), (3, (0, 1)), (4, (0, 1)), (5, (0, 1)), (6, (0,)), (7, (0, 1)), (8, (0, 1)), (9, (0, 1)), (10, (0, 1)), (11, (0, 1)), (12, (0, 1)), (13, (0, 1)), (14, (0, 1)), (15, (0, 1)))": 0.08695652173913043,
        "((0, (0, 1)), (1, (0, 1)), (2, (0, 1)), (3, (0, 1)), (4, (1,)), (5, (0, 1)), (6, (0,)), (7, (0, 1)), (8, (0, 1)), (9, (0, 1)), (10, (0, 1)), (11, (0, 1)), (12, (0, 1)), (13, (0, 1)), (14, (0, 1)), (15, (0, 1)))": 0.08695652173913043,
        "RANDOM": 0.6086956521739129,
        "MAX": [
          16,
          15,
          -1,
          1967
        ]
      },
      "1006": {
        "((0, (0,)), (1, (-1, 0, 1, 2, 3)), (2, (-1, 0, 1, 2, 3)), (3, (-1, 0, 1, 2, 3)), (4, (-1, 0, 1, 2, 3)), (5, (-1, 0, 1, 2)), (6, (-1, 0, 2)))": 0.08695652173913043,
        "((0, (0, 1, 2)), (1, (-1, 0, 1, 2, 3)), (2, (-1, 0, 1, 2, 3)), (3, (0, 1, 2, 3)), (4, (-1, 0, 1, 2, 3)), (5, (-1, 0, 1, 2)), (6, (-1, 0, 1, 2)))": 0.08695652173913043,
        "((0, (0,)), (1, (-1, 0)), (2, (-1, 0)), (3, (-1, 0)), (4, (-1, 0)), (5, (0,)), (6, (-1, 0)), (7, (-1, 0)), (8, (0,)), (9, (-1, 0)), (10, (-1, 0)), (11, (-1, 0)), (12, (-1, 0)), (13, (-1, 0)), (14, (-1, 0)), (15, (-1, 0)))": 0.06521739130434782,
        "((0, (0, -2)), (1, (-3, -2, -1, 0, 1)), (2, (-1, 0, -2)), (3, (-1, 0, -3, -2)), (4, (0, -3, -2)), (5, (-4, -3, -2, -1, 0)), (6, (-4, -3, -2, -1, 0)))": 0.06521739130434782,
        "RANDOM": 0.6956521739130431,
        "MAX": [
          16,
          15,
          -4,
          4
        ]
      }
    }
  },
  "31": {
    "FF": {
      "1006": 1.0
    },
    "PF": {
      "1006": {
        "((0, (0,)), (1, (0, 1)), (2, (0, 1)), (3, (0, 1)), (4, (0, 1)), (5, (0, 1)), (6, (0, 1)), (7, (0, 1)), (8, (0, 1)), (9, (0, 1)), (10, (0, 1)), (11, (0, 1)), (12, (0, 1)), (13, (0,)), (14, (0, 1)), (15, (0, 1)))": 0.061855670103092786,
        "RANDOM": 0.9381443298969069,
        "MAX": [
          16,
          15,
          -4,
          4
        ]
      }
    }
  },
  "32": {
    "FF": {
      "1006": 1.0
    },
    "PF": {
      "1006": {
        "((0, (0, 1)), (1, (0, 1)), (2, (0, 1)), (3, (0, 1)), (4, (0, 1)), (5, (0, 1)), (6, (0, 1)), (7, (0, 1)), (8, (0, 1)), (9, (0, 1)), (10, (0, 1)), (11, (0, 1)), (12, (0, 1)), (13, (0, 1)), (14, (0, 1)), (15, (0, 1)))": 0.5434083601286174,
        "((0, (0, 1, 2, -1)), (1, (-1, 0, 1, 2, 3)), (2, (-1, 0, 1, 2, 3)), (3, (0, 1, 2, -1)), (4, (0, 1, 2, -1)), (5, (0, 1, 2, -1)), (6, (-2, -1, 0, 1, 2)))": 0.08360128617363344,
        "((0, (0, 1, -2, -1)), (1, (-2, -1, 0, 1, 2)), (2, (0, 1, -2, -1)), (3, (0, 1, -2, -1)), (4, (0, 1, -2, -1)), (5, (-3, -2, -1, 0, 1)), (6, (-3, -2, -1, 0, 1)))": 0.08038585209003216,
        "((0, (0, 1, 2)), (1, (-1, 0, 1, 2, 3)), (2, (-1, 0, 1, 2, 3)), (3, (-1, 0, 1, 2, 3)), (4, (-1, 0, 1, 2, 3)), (5, (-1, 0, 1, 2)), (6, (-1, 0, 1, 2)))": 0.0707395498392283,
        "((0, (0, 1, 2, 3)), (1, (0, 1, 2, 3)), (2, (0, 1, 2, 3)), (3, (-1, 0, 1, 2, 3)), (4, (-1, 0, 1, 2, 3)), (5, (-1, 0, 1, 2, 3)), (6, (-1, 0, 1, 2, 3)))": 0.06109324758842444,
        "((0, (0, 1, 2, 3)), (1, (0, 1, 2, 3, 4)), (2, (0, 1, 2, 3, 4)), (3, (0, 1, 2, 3, 4)), (4, (0, 1, 2, 3)), (5, (0, 1, 2, 3)), (6, (0, 1, 2, 3)))": 0.05787781350482315,
        "((0, (0, 1, 2)), (1, (0, 1, 2, 3)), (2, (-1, 0, 1, 2, 3)), (3, (-1, 0, 1, 2, 3)), (4, (-1, 0, 1, 2, 3)), (5, (-1, 0, 1, 2, 3)), (6, (-1, 0, 1, 2)))": 0.05144694533762058,
        "((0, (0, -3, -2, -1)), (1, (0, -3, -2, -1)), (2, (0, -3, -2, -1)), (3, (0, -3, -2, -1)), (4, (-4, -3, -2, -1, 0)), (5, (-4, -3, -2, -1, 0)), (6, (-4, -3, -2, -1, 0)))": 0.05144694533762058,
        "RANDOM": 0,
        "MAX": [
          16,
          15,
          -4,
          4
        ]
      }
    }
  },
  "33": {
    "FF": {
      "1007": 1.0
    },
    "PF": {
      "1007": {
        "((0, (2929, 2678, -2, 0, 2)), (1, (1, 2929, 2845, 2678)), (2, (2929, 2678, 2845, -2, -1, 0)), (3, (2678, 2845, -2, 0, 2594)), (4, (0, 2761, 2594)), (5, (-3, -2, 2845, 0, 1, 2594)), (6, (0, 1, 2594, -1)))": 1.0,
        "RANDOM": 0,
        "MAX": [
          7,
          6,
          -3,
          2929
        ]
      }
    }
  },
  "36": {
    "FF": {
      "1007": 1.0
    },
    "PF": {
      "1007": {
        "((0, (977, -1, 0, 1, 1061)), (1, (977, 1144, 0, 1, 643)), (2, (1144, -3, -1, 0)), (3, (977, 893, -3, 0, 1)), (4, (1144, 893, -2, 0, 1, 1060)), (5, (1144, 893, -3, -2, 1, 642, 1060)), (6, (1060, 893, -2, 642)))": 1.0,
        "RANDOM": 0,
        "MAX": [
          7,
          6,
          -3,
          1144
        ]
      }
    }
  },
  "1": {
    "RANDOM": 1
  }
}